corneto/__init__.py
corneto/_constants.py
corneto/_core.py
corneto/_data.py
corneto/_decorators.py
corneto/_graph.py
corneto/_io.py
corneto/_legacy.py
corneto/_logging.py
corneto/_ml.py
corneto/_nx.py
corneto/_plotting.py
corneto/_settings.py
corneto/_types.py
corneto/_typing.py
corneto/_util.py
corneto/backend/__init__.py
corneto/backend/_base.py
corneto/backend/_cvxpy_backend.py
corneto/backend/_picos_backend.py
corneto/contrib/__init__.py
corneto/contrib/_util.py
corneto/contrib/networkx.py
corneto/data/__init__.py
corneto/data/_base.py
corneto/data/_dataset.py
corneto/data/_pkn.py
corneto/data/util.py
corneto/experimental/__init__.py
corneto/extensions/__init__.py
corneto/extensions/_numba.py
corneto/extensions/_optional.py
corneto/graph/__init__.py
corneto/graph/_base.py
corneto/graph/_graph.py
corneto/graph/_random.py
corneto/io/__init__.py
corneto/io/_base.py
corneto/io/_graphio.py
corneto/io/_metabolism.py
corneto/io/_signaling.py
corneto/io/_util.py
corneto/methods/__init__.py
corneto/methods/carnival.py
corneto/methods/future/__init__.py
corneto/methods/future/carnival.py
corneto/methods/future/fba.py
corneto/methods/future/imat.py
corneto/methods/future/method.py
corneto/methods/future/pcst.py
corneto/methods/future/sampler.py
corneto/methods/future/steiner.py
corneto/methods/future/steiner_pcst.py
corneto/methods/metabolism/__init__.py
corneto/methods/metabolism/_utils.py
corneto/methods/metabolism/fba.py
corneto/methods/method.py
corneto/methods/sampler.py
corneto/methods/shortest_path.py
corneto/methods/signal/__init__.py
corneto/methods/signal/_util.py
corneto/methods/signal/cellnopt_ilp.py
corneto/methods/signaling.py
corneto/methods/signalling/__init__.py
corneto/methods/signalling/carnival.py
corneto/methods/steiner.py
corneto/resources/citations.bib
corneto/resources/corneto-logo-128px.png
corneto/resources/corneto-logo-256px.png
corneto/resources/corneto-logo-512px.png
corneto/resources/logo.png
corneto/utils/__init__.py
corneto/utils/_attr.py
corneto-1.0.0b2.dist-info/LICENSE
corneto-1.0.0b2.dist-info/METADATA
corneto-1.0.0b2.dist-info/WHEEL
corneto-1.0.0b2.dist-info/RECORD
