Metadata-Version: 2.3
Name: corneto
Version: 1.0.0b2
Summary: CORNETO: A Unified Framework for Omics-Driven Network Inference
License: GPL-3.0-or-later
Author: Pablo Rodriguez-Mier
Author-email: pablo.rodriguez-mier@uni-heidelberg.de
Requires-Python: >=3.10
Classifier: Development Status :: 3 - Alpha
Classifier: Intended Audience :: Developers
Classifier: Intended Audience :: Science/Research
Classifier: License :: OSI Approved :: GNU General Public License v3 (GPLv3)
Classifier: License :: OSI Approved :: GNU General Public License v3 or later (GPLv3+)
Classifier: Programming Language :: Python :: 3
Classifier: Programming Language :: Python :: 3.10
Classifier: Programming Language :: Python :: 3.11
Classifier: Programming Language :: Python :: 3.12
Classifier: Programming Language :: Python :: 3.13
Classifier: Topic :: Scientific/Engineering :: Bio-Informatics
Classifier: Topic :: Scientific/Engineering :: Mathematics
Classifier: Topic :: Software Development :: Libraries :: Python Modules
Provides-Extra: ml
Provides-Extra: os
Provides-Extra: research
Provides-Extra: vanilla
Requires-Dist: PICOS (>=2.6.0) ; extra == "research"
Requires-Dist: cobra (>=0.29.0) ; extra == "research"
Requires-Dist: cvxpy (>=1.5.1) ; extra == "ml"
Requires-Dist: cvxpy (>=1.5.1) ; extra == "os"
Requires-Dist: cvxpy (>=1.5.1) ; extra == "research"
Requires-Dist: cvxpy-base (>=1.5.1)
Requires-Dist: cvxpy-base (>=1.5.1) ; extra == "vanilla"
Requires-Dist: graphviz (>=0.20.1) ; extra == "os"
Requires-Dist: graphviz (>=0.20.1) ; extra == "research"
Requires-Dist: gurobipy ; extra == "research"
Requires-Dist: highspy (>=1.9.0) ; extra == "os"
Requires-Dist: highspy (>=1.9.0) ; extra == "research"
Requires-Dist: jax (>=0.6.1) ; extra == "ml"
Requires-Dist: keras (>=3.8.0) ; extra == "ml"
Requires-Dist: matplotlib (>=3.5.2) ; extra == "os"
Requires-Dist: matplotlib (>=3.5.2) ; extra == "research"
Requires-Dist: networkx (>=3.2.1) ; extra == "os"
Requires-Dist: networkx (>=3.2.1) ; extra == "research"
Requires-Dist: pandas (>=2.2.3) ; extra == "ml"
Requires-Dist: pandas (>=2.2.3) ; extra == "research"
Requires-Dist: pcst-fast (>=1.0.10) ; extra == "research"
Requires-Dist: pyscipopt (>=5.4.1) ; extra == "os"
Requires-Dist: pyscipopt (>=5.4.1) ; extra == "research"
Requires-Dist: scikit-learn (>=1.6.0) ; extra == "ml"
Requires-Dist: scipy (>=1.14.1)
Requires-Dist: scipy (>=1.14.1) ; extra == "ml"
Requires-Dist: scipy (>=1.14.1) ; extra == "os"
Requires-Dist: scipy (>=1.14.1) ; extra == "research"
Requires-Dist: scipy (>=1.14.1) ; extra == "vanilla"
Project-URL: Homepage, https://github.com/saezlab/corneto/
Project-URL: Repository, https://github.com/saezlab/corneto/
